OSGridConverter/__init__.py
OSGridConverter/base.py
OSGridConverter/grid.py
OSGridConverter/latlong.py
OSGridConverter/cartesian/__init__.py
OSGridConverter/cartesian/algebra.py
OSGridConverter/cartesian/transform.py
OSGridConverter/cartesian/vector.py
OSGridConverter/mapping/__init__.py
OSGridConverter/mapping/defaultGrid.py
OSGridConverter/mapping/ellipsoids.py
OSGridConverter-0.1.3.dist-info/DESCRIPTION.rst
OSGridConverter-0.1.3.dist-info/METADATA
OSGridConverter-0.1.3.dist-info/RECORD
OSGridConverter-0.1.3.dist-info/WHEEL
OSGridConverter-0.1.3.dist-info/metadata.json
OSGridConverter-0.1.3.dist-info/top_level.txt
test/__init__.py
test/baseTest.py
test/test_algebra.py
test/test_script.py
test/types.py
